<MAIN>
	<OBJECTS>
		<OBJECT name="Door Panel">
			<texto> It opens the door </texto>
			<texto> Opening the door </texto>
		</OBJECT>
		<OBJECT name="Room Door">
			<texto> My room's door </texto>
			<texto> Doesn´t work this way </texto>
		</OBJECT>
		<OBJECT name="Bed">
			<texto> My bed </texto>
			<texto> I should make it </texto>
		</OBJECT>
		<OBJECT name="Painter">
			<texto> The painter </texto>
			<texto> An angry old bastard </texto>
		</OBJECT>
		<OBJECT name="Paint Cube">
			<texto> A cube full of paint </texto>
			<texto> It would be a shame if someone throwed it </texto>
		</OBJECT>
	</OBJECTS>
	<CONVERSATIONS>
		<CONVERSATION name="Painter">
			<texto> Ey you! </texto>
			<texto> Don´t touch the paint! </texto>
		</CONVERSATION>
	</CONVERSATIONS>
	<EVENTS>
		<EVENT name="Event1">
			<texto> What the...? </texto>
			<texto> ARE YOU MAD!? </texto>
			<texto> Let me help you </texto>
		</EVENT>
	</EVENTS>
</MAIN>